{
  "artists": [
    {
      "id": 1,
      "name": "The Strokes",
      "genre": "Rock",
      "urlImg": "https://i.scdn.co/image/ab67616100005174c3b137793230f4043feb0089"
    },
    {
      "id": 2,
      "name": "blink-182",
      "genre": "Rock",
      "urlImg": "https://i.scdn.co/image/ab6761610000e5eb5da36f8b98dd965336a1507a"
    },
    {
      "id": 3,
      "name": "Supercombo",
      "genre": "Rock",
      "urlImg": "https://i.scdn.co/image/ab67616d0000b27323ad7415e0d5fe197db5f321"
    },
    {
      "id": 4,
      "name": "Queen",
      "genre": "Rock",
      "urlImg": "https://i.scdn.co/image/b040846ceba13c3e9c125d68389491094e7f2982"
    },
    {
      "id": 5,
      "name": "Nirvana",
      "genre": "Rock",
      "urlImg": "https://i.scdn.co/image/84282c28d851a700132356381fcfbadc67ff498b"
    }
  ]
}